[
  {
    "path": "010000000",
    "code": 35,
    "name": "Jihočeský kraj",
    "id": 3,
    "points": [
      {
        "lon": 16.730591892366263,
        "lat": 48.96732249103212
      },
      {
        "lon": 16.789776566487134,
        "lat": 48.98985109255166
      },
      {
        "lon": 16.8490948085259,
        "lat": 48.96735284290534
      },
      {
        "lon": 16.8490948085259,
        "lat": 48.92238676260941
      },
      {
        "lon": 16.78985667292234,
        "lat": 48.899888549069836
      },
      {
        "lon": 16.730591892366263,
        "lat": 48.922356410736185
      }
    ]
  },
  {
    "path": "020000000",
    "code": 43,
    "name": "Plzeňský kraj",
    "id": 4,
    "points": [
      {
        "lon": 16.671113337946142,
        "lat": 49.03478674872838
      },
      {
        "lon": 16.730377918559775,
        "lat": 49.05731545869851
      },
      {
        "lon": 16.789776566487134,
        "lat": 49.03481717284759
      },
      {
        "lon": 16.789776566487134,
        "lat": 48.98985109255166
      },
      {
        "lon": 16.730458324448367,
        "lat": 48.96735284290534
      },
      {
        "lon": 16.671113337946142,
        "lat": 48.98982066843243
      }
    ]
  },
  {
    "path": "030000000",
    "code": 108,
    "name": "Kraj Vysočina",
    "id": 10,
    "points": [
      {
        "lon": 16.90940873687522,
        "lat": 49.03472546485316
      },
      {
        "lon": 16.968673244767363,
        "lat": 49.05725417472468
      },
      {
        "lon": 17.028071819518495,
        "lat": 49.03475588890669
      },
      {
        "lon": 17.028071819518495,
        "lat": 48.989789808610745
      },
      {
        "lon": 16.968753650383285,
        "lat": 48.967291558997275
      },
      {
        "lon": 16.90940873687522,
        "lat": 48.989759384557225
      }
    ]
  },
  {
    "path": "040000000",
    "code": 132,
    "name": "Moravskoslezský kraj",
    "id": 13,
    "points": [
      {
        "lon": 17.08814442846829,
        "lat": 49.10212847474995
      },
      {
        "lon": 17.147489068077665,
        "lat": 49.12465729326715
      },
      {
        "lon": 17.206968275890194,
        "lat": 49.1021589711793
      },
      {
        "lon": 17.206968275890194,
        "lat": 49.057192890883364
      },
      {
        "lon": 17.14756977431489,
        "lat": 49.034694605098295
      },
      {
        "lon": 17.08814442846829,
        "lat": 49.05716239445401
      }
    ]
  },
  {
    "path": "050000000",
    "code": 141,
    "name": "Zlínský kraj",
    "id": 14,
    "points": [
      {
        "lon": 17.147703840719142,
        "lat": 49.03466418111047
      },
      {
        "lon": 17.206968275890194,
        "lat": 49.057192890883364
      },
      {
        "lon": 17.2663667774655,
        "lat": 49.034694605098295
      },
      {
        "lon": 17.2663667774655,
        "lat": 48.989728524802345
      },
      {
        "lon": 17.207048681233438,
        "lat": 48.967230275221716
      },
      {
        "lon": 17.147703840719142,
        "lat": 48.98969810081454
      }
    ]
  },
  {
    "path": "060000000",
    "code": 78,
    "name": "Liberecký kraj",
    "id": 21,
    "points": [
      {
        "lon": 16.909193963505025,
        "lat": 49.16968465743742
      },
      {
        "lon": 16.968781299417813,
        "lat": 49.19215237398973
      },
      {
        "lon": 17.02834155267689,
        "lat": 49.169654015483694
      },
      {
        "lon": 17.02834155267689,
        "lat": 49.12468793518776
      },
      {
        "lon": 16.968862308139506,
        "lat": 49.1021896130834
      },
      {
        "lon": 16.90935611881385,
        "lat": 49.124657366086964
      }
    ]
  },
  {
    "path": "070000000",
    "code": 116,
    "name": "Jihomoravský kraj",
    "id": 415,
    "points": [
      {
        "lon": 16.968887217848625,
        "lat": 48.967261207189566
      },
      {
        "lon": 17.028071819518495,
        "lat": 48.989789808610745
      },
      {
        "lon": 17.087389988653708,
        "lat": 48.967291558997275
      },
      {
        "lon": 17.087389988653708,
        "lat": 48.92232547870133
      },
      {
        "lon": 17.028151925682337,
        "lat": 48.899827265194524
      },
      {
        "lon": 16.968887217848625,
        "lat": 48.922295126893644
      }
    ]
  },
  {
    "path": "080000000",
    "code": 124,
    "name": "Olomoucký kraj",
    "id": 416,
    "points": [
      {
        "lon": 17.02855632568273,
        "lat": 49.034694822965264
      },
      {
        "lon": 17.08782079721427,
        "lat": 49.057223532787454
      },
      {
        "lon": 17.14721933537744,
        "lat": 49.03472524698593
      },
      {
        "lon": 17.14721933537744,
        "lat": 48.98975916668999
      },
      {
        "lon": 17.087901202693857,
        "lat": 48.96726091709294
      },
      {
        "lon": 17.02855632568273,
        "lat": 48.98972874266933
      }
    ]
  },
  {
    "path": "090000000",
    "code": 94,
    "name": "Pardubický kraj",
    "id": 817,
    "points": [
      {
        "lon": 16.96899687657112,
        "lat": 49.1021591166211
      },
      {
        "lon": 17.02834155267689,
        "lat": 49.12468793518776
      },
      {
        "lon": 17.08782079721427,
        "lat": 49.1021896130834
      },
      {
        "lon": 17.08782079721427,
        "lat": 49.057223532787454
      },
      {
        "lon": 17.028422259051105,
        "lat": 49.03472524698593
      },
      {
        "lon": 16.96899687657112,
        "lat": 49.05719303632516
      }
    ]
  },
  {
    "path": "100000000",
    "code": 51,
    "name": "Karlovarský kraj",
    "id": 2015,
    "points": [
      {
        "lon": 16.611553778251665,
        "lat": 49.102251042433316
      },
      {
        "lon": 16.670898563847217,
        "lat": 49.12477986114834
      },
      {
        "lon": 16.730377918559775,
        "lat": 49.10228153899445
      },
      {
        "lon": 16.730377918559775,
        "lat": 49.05731545869851
      },
      {
        "lon": 16.670979270632415,
        "lat": 49.03481717284759
      },
      {
        "lon": 16.611553778251665,
        "lat": 49.05728496213738
      }
    ]
  },
  {
    "path": "110000000",
    "code": 60,
    "name": "Ústecký kraj",
    "id": 2016,
    "points": [
      {
        "lon": 16.79004630056187,
        "lat": 49.16971529942429
      },
      {
        "lon": 16.849633673383337,
        "lat": 49.19218301596002
      },
      {
        "lon": 16.909193963505025,
        "lat": 49.16968465743742
      },
      {
        "lon": 16.909193963505025,
        "lat": 49.124718577141486
      },
      {
        "lon": 16.849714682242688,
        "lat": 49.10222025502062
      },
      {
        "lon": 16.790208456146328,
        "lat": 49.12468800800765
      }
    ]
  },
  {
    "path": "120000000",
    "code": 19,
    "name": "Hlavní město Praha",
    "id": 2815,
    "points": [
      {
        "lon": 16.730701551463017,
        "lat": 49.10222040046281
      },
      {
        "lon": 16.79004630056187,
        "lat": 49.12474921912836
      },
      {
        "lon": 16.84952561854927,
        "lat": 49.10225089699099
      },
      {
        "lon": 16.84952561854927,
        "lat": 49.057284816695045
      },
      {
        "lon": 16.790127007210074,
        "lat": 49.034786530860586
      },
      {
        "lon": 16.730701551463014,
        "lat": 49.05725432016688
      }
    ]
  },
  {
    "path": "130000000",
    "code": 27,
    "name": "Středočeský kraj",
    "id": 3215,
    "points": [
      {
        "lon": 16.79026107429643,
        "lat": 49.0347561067742
      },
      {
        "lon": 16.84952561854927,
        "lat": 49.057284816695045
      },
      {
        "lon": 16.908924229888463,
        "lat": 49.034786530860586
      },
      {
        "lon": 16.908924229888463,
        "lat": 48.98982045056466
      },
      {
        "lon": 16.849606024301522,
        "lat": 48.96732220093477
      },
      {
        "lon": 16.79026107429643,
        "lat": 48.989790026478275
      }
    ]
  },
  {
    "path": "140000000",
    "code": 86,
    "name": "Královéhradecký kraj",
    "id": 3216,
    "points": [
      {
        "lon": 16.849849250902764,
        "lat": 49.102189758525384
      },
      {
        "lon": 16.909193963505025,
        "lat": 49.124718577141486
      },
      {
        "lon": 16.968673244767363,
        "lat": 49.10222025502062
      },
      {
        "lon": 16.968673244767363,
        "lat": 49.05725417472468
      },
      {
        "lon": 16.909274670016234,
        "lat": 49.03475588890669
      },
      {
        "lon": 16.84984925090276,
        "lat": 49.05722367822945
      }
    ]
  }
]